pynext/__init__.py
pynext/__main__.py
pynext/client.py
pynext/debug.py
pynext/enums.py
pynext/errors.py
pynext/selfbot.py
pynext/state.py
pynext/types.py
pynext/utils.py
pynext/discord/__init__.py
pynext/discord/abc.py
pynext/discord/activity.py
pynext/discord/application.py
pynext/discord/attachment.py
pynext/discord/banentry.py
pynext/discord/channel.py
pynext/discord/color.py
pynext/discord/discorduser.py
pynext/discord/emoji.py
pynext/discord/file.py
pynext/discord/guild.py
pynext/discord/image.py
pynext/discord/member.py
pynext/discord/message.py
pynext/discord/permissions.py
pynext/discord/presence.py
pynext/discord/reaction.py
pynext/discord/role.py
pynext/discord/slash_command.py
pynext/gateway/__init__.py
pynext/gateway/dispatcher.py
pynext/gateway/parser.py
pynext/gateway/response.py
pynext/gateway/websocket.py
pynext/rest/__init__.py
pynext/rest/httpclient.py
pynext/rest/manager.py
pynext/rest/route.py
pynext-1.2.0.dist-info/LICENSE
pynext-1.2.0.dist-info/METADATA
pynext-1.2.0.dist-info/WHEEL
pynext-1.2.0.dist-info/top_level.txt
pynext-1.2.0.dist-info/RECORD
