Metadata-Version: 2.1
Name: pynext
Version: 1.2.0
Summary: Library that will allow you to manage selfbots.
Home-page: https://github.com/xxenvy/pynext
Author: xXenvy
Author-email: <xpimpek01@gmail.com>
License: MIT
Project-URL: Documentation, https://pynext.readthedocs.io/en/latest/
Project-URL: Issue tracker, https://github.com//xxenvy/pynext/issues
Keywords: python,requests,discord selfbot,selfbot,discord.py,aiohttp,nextcord,pycord
Classifier: Development Status :: 1 - Planning
Classifier: Intended Audience :: Developers
Classifier: License :: OSI Approved :: MIT License
Classifier: Natural Language :: English
Classifier: Programming Language :: Python :: 3.9
Classifier: Programming Language :: Python :: 3.10
Classifier: Programming Language :: Python :: 3.11
Classifier: Framework :: AsyncIO
Classifier: Framework :: aiohttp
Classifier: Topic :: Software Development :: Libraries
Classifier: Topic :: Software Development :: Libraries :: Python Modules
Classifier: Operating System :: Unix
Classifier: Operating System :: MacOS :: MacOS X
Classifier: Operating System :: Microsoft :: Windows
Classifier: Typing :: Typed
Requires-Python: >=3.9.0
License-File: LICENSE
Requires-Dist: colorlog >=6.7.0
Requires-Dist: aiohttp >=3.8.0
Provides-Extra: speed
Requires-Dist: orjson ; extra == 'speed'
Requires-Dist: aiohttp[speedups] ; extra == 'speed'
